{"previousPageIsFirst":false,"previous":"c2VhYWRlMjAxNi52bg==","list":[{"id":"www.codepreneur.io","filename":"www.codepreneur.io.md","title":"codepreneur.io","url":"https://www.codepreneur.io/","source":"https://github.com/codepreneur/site","showcaseTags":["blog"]},{"id":"www.webstackdev.com","filename":"www.webstackdev.com.md","title":"WebStackDev","url":"https://www.webstackdev.com","showcaseTags":["blog","learning"]},{"id":"zenika.com","filename":"zenika.com.md","title":"Zenika","url":"https://zenika.com/","showcaseTags":["business","multi-languages"]}],"hasNextPage":false,"hasPreviousPage":true}